kiru-0.1.11.dist-info/METADATA
kiru-0.1.11.dist-info/WHEEL
kiru/__init__.py
kiru/__init__.pyi
kiru/kiru.cpython-311-s390x-linux-gnu.so
kiru/py.typed
kiru-0.1.11.dist-info/RECORD
