Metadata-Version: 2.4
Name: kiru
Version: 0.1.11
Classifier: Programming Language :: Rust
Classifier: Programming Language :: Python :: Implementation :: CPython
Classifier: Programming Language :: Python :: Implementation :: PyPy
Keywords: text,chunking,nlp,rag
Requires-Python: >=3.11
Project-URL: Homepage, https://github.com/bitswired/kiru
Project-URL: Repository, https://github.com/bitswired/kiru
Project-URL: Documentation, https://github.com/bitswired/kiru
Project-URL: Bug Tracker, https://github.com/bitswired/kiru/issues
Project-URL: Changelog, https://github.com/bitswired/kiru/releases
